tests/__init__.py
tests/test_typestruct.py
typestruct/__init__.py
typestruct/types.py
typestruct-0.1.1.dist-info/METADATA
typestruct-0.1.1.dist-info/RECORD
typestruct-0.1.1.dist-info/WHEEL
typestruct-0.1.1.dist-info/top_level.txt
