Metadata-Version: 2.1
Name: typestruct
Version: 0.1.1
Summary: struct serialization/deserialization with typing
Home-page: https://github.com/fanzeyi/typestruct
Author: Zeyi Fan
Author-email: i@zr.is
License: UNKNOWN
Platform: UNKNOWN
Classifier: Programming Language :: Python :: 3
Classifier: License :: OSI Approved :: MIT License
Classifier: Operating System :: OS Independent
